easyrtc/CameraStream.py
easyrtc/DataStream.py
easyrtc/WebRTCClient.py
easyrtc/WebRTCServer.py
easyrtc/__init__.py
easyrtc-0.0.2.dist-info/licenses/LICENSE.txt
easyrtc-0.0.2.dist-info/METADATA
easyrtc-0.0.2.dist-info/WHEEL
easyrtc-0.0.2.dist-info/top_level.txt
easyrtc-0.0.2.dist-info/RECORD
