Metadata-Version: 2.4
Name: easyrtc
Version: 0.0.2
Summary: A lightweight Python WebRTC streaming server-client using aiortc and OpenCV.
Author-email: Kayra Aytug <kayraaytug@outlook.com>
Maintainer-email: Kayra Aytug <kayraaytug@outlook.com>
License: MIT License
Project-URL: Homepage, https://github.com/kayraaytug/easyrtc
Project-URL: Repository, https://github.com/kayraaytug/easyrtc
Project-URL: Bug Reports, https://github.com/kayraaytug/easyrtc/issues
Keywords: webrtc,stream,camera,opencv
Classifier: Development Status :: 3 - Alpha
Classifier: Intended Audience :: Developers
Classifier: Topic :: Software Development :: Build Tools
Classifier: License :: OSI Approved :: MIT License
Classifier: Programming Language :: Python :: 3
Classifier: Programming Language :: Python :: 3.9
Classifier: Programming Language :: Python :: 3.10
Classifier: Programming Language :: Python :: 3.11
Classifier: Programming Language :: Python :: 3.12
Classifier: Programming Language :: Python :: 3.13
Classifier: Programming Language :: Python :: 3 :: Only
Requires-Python: >=3.9
License-File: LICENSE.txt
Requires-Dist: aiortc>=1.4.0
Requires-Dist: opencv-python>=4.9.0.80
Requires-Dist: av>=10.0.0
Requires-Dist: numpy>=1.26.0
Dynamic: license-file
